huang_rick_portal_gun/__init__.py
huang_rick_portal_gun/__main__.py
huang_rick_portal_gun/main.py
huang_rick_portal_gun-0.1.2.dist-info/METADATA
huang_rick_portal_gun-0.1.2.dist-info/WHEEL
huang_rick_portal_gun-0.1.2.dist-info/entry_points.txt
huang_rick_portal_gun-0.1.2.dist-info/RECORD
